[
  {
    "session_id": "SES_001",
    "section_id": "SEC_CS240_01",
    "date": "2026-01-12",
    "topic": "Course Intro and C++ Review",
    "delivery": "in_person"
  },
  {
    "session_id": "SES_002",
    "section_id": "SEC_CS240_01",
    "date": "2026-01-14",
    "topic": "Arrays, Vectors, and Complexity",
    "delivery": "in_person"
  },
  {
    "session_id": "SES_003",
    "section_id": "SEC_CS240_01",
    "date": "2026-01-19",
    "topic": "Linked Lists",
    "delivery": "in_person"
  },
  {
    "session_id": "SES_004",
    "section_id": "SEC_CS240_01",
    "date": "2026-01-21",
    "topic": "Stacks and Queues",
    "delivery": "in_person"
  }
]
